langchain_openai/__init__.py
langchain_openai/chat_models/__init__.py
langchain_openai/chat_models/azure.py
langchain_openai/chat_models/base.py
langchain_openai/embeddings/__init__.py
langchain_openai/embeddings/azure.py
langchain_openai/embeddings/base.py
langchain_openai/llms/__init__.py
langchain_openai/llms/azure.py
langchain_openai/llms/base.py
langchain_openai/output_parsers/__init__.py
langchain_openai/output_parsers/tools.py
langchain_openai/py.typed
gigachain_openai-0.1.22.dist-info/LICENSE
gigachain_openai-0.1.22.dist-info/METADATA
gigachain_openai-0.1.22.dist-info/WHEEL
gigachain_openai-0.1.22.dist-info/RECORD
